setup.py
recordeggs/__init__.py
recordeggs/recordeggs.py
recordeggs.egg-info/PKG-INFO
recordeggs.egg-info/SOURCES.txt
recordeggs.egg-info/dependency_links.txt
recordeggs.egg-info/entry_points.txt
recordeggs.egg-info/not-zip-safe
recordeggs.egg-info/top_level.txt