Metadata-Version: 1.0
Name: recordeggs
Version: 0.3.0
Summary: Captures easy_install command output to download source files
Home-page: https://launchpad.net/recordeggs
Author: Mike C. Fletcher
Author-email: mcfletch@vrplumber.com
License: BSD
Download-URL: https://launchpad.net/recordeggs/+download
Keywords: easy_install,deployment,packages,reproduce,capture,hack
Platform: Linux
Classifier: Programming Language :: Python
Classifier: Topic :: Software Development :: Libraries :: Python Modules
Classifier: Intended Audience :: Developers
